simian/__init__.py
simian/patch.py
simian/reload.py
simian-2.0.0.dist-info/top_level.txt
simian-2.0.0.dist-info/METADATA
simian-2.0.0.dist-info/DESCRIPTION.rst
simian-2.0.0.dist-info/metadata.json
simian-2.0.0.dist-info/WHEEL
simian-2.0.0.dist-info/RECORD
