Metadata-Version: 2.0
Name: simian
Version: 2.0.0
Summary: A decorator for easily mocking out multiple dependencies by monkey-patching.
Home-page: https://github.com/themattrix/python-simian
Author: Matthew Tardiff
Author-email: mattrix@gmail.com
License: MIT
Platform: UNKNOWN
Classifier: Topic :: Software Development :: Testing
Classifier: License :: OSI Approved :: MIT License
Classifier: Programming Language :: Python :: 2
Classifier: Programming Language :: Python :: 2.6
Classifier: Programming Language :: Python :: 2.7
Classifier: Programming Language :: Python :: 3
Classifier: Programming Language :: Python :: 3.2
Classifier: Programming Language :: Python :: 3.3
Classifier: Programming Language :: Python :: 3.4
Classifier: Programming Language :: Python :: Implementation :: CPython
Classifier: Programming Language :: Python :: Implementation :: PyPy
Requires-Dist: mock
Requires-Dist: contextlib2
